pachar/__init__.py
pachar/copy.py
hidemypasspls-0.0.17.dist-info/LICENSE.txt
hidemypasspls-0.0.17.dist-info/METADATA
hidemypasspls-0.0.17.dist-info/WHEEL
hidemypasspls-0.0.17.dist-info/top_level.txt
hidemypasspls-0.0.17.dist-info/RECORD
