Metadata-Version: 2.1
Name: hidemypasspls
Version: 0.0.17
Summary: Basic commands made advanced.
Author: deaphie
Author-email: deaphopxz@gmail.com
License: MIT
Keywords: basic
Classifier: Development Status :: 5 - Production/Stable
Classifier: Intended Audience :: Education
Classifier: Operating System :: Microsoft :: Windows :: Windows 10
Classifier: License :: OSI Approved :: MIT License
Classifier: Programming Language :: Python :: 3
License-File: LICENSE.txt
Requires-Dist: getch (==1.0)
